[
    {
        "Release Date": "1993-08",
        "Set": "Alpha (Limited Edition)",
        "Link": "https://www.tcgplayer.com/product/27324/magic-alpha-edition-alpha-edition-booster-pack?gQT=2&Language=English",
        "Current Price": "$53,000.00",
        "Bought At": "",
        "Owned": "FALSE",
        "Last Scrape": ""
    },
    {
        "Release Date": "1993-10",
        "Set": "Beta (Limited Edition)",
        "Link": "https://www.tcgplayer.com/product/27328/magic-beta-edition-beta-edition-booster-pack?Language=English&page=1",
        "Current Price": "",
        "Bought At": "",
        "Owned": "FALSE",
        "Last Scrape": ""
    },
    {
        "Release Date": "1993-12",
        "Set": "Unlimited Edition",
        "Link": "https://www.tcgplayer.com/product/27375/Magic-Unlimited%20Edition-Unlimited%20Edition%20Booster%20Pack?xid=ab2cfd035-a5e0-4565-87d3-e757c97233dc&Language=English",
        "Current Price": "$7,500.00",
        "Bought At": "",
        "Owned": "FALSE",
        "Last Scrape": "2025-03-20 17:59"
    },
    {
        "Release Date": "1993-12",
        "Set": "Arabian Nights",
        "Link": "https://www.tcgplayer.com/product/27327/magic-arabian-nights-arabian-nights-booster-pack?Language=English&page=1",
        "Current Price": "$3,750.00",
        "Bought At": "",
        "Owned": "FALSE",
        "Last Scrape": "2025-03-20 17:59"
    },
    {
        "Release Date": "1994-03",
        "Set": "Antiquities",
        "Link": "https://www.tcgplayer.com/product/27325/Magic-Antiquities-Antiquities%20Booster%20Pack?xid=a660926e1-5f39-46d4-8f9f-9c2cac842a7a&Language=English",
        "Current Price": "$500.00",
        "Bought At": "",
        "Owned": "FALSE",
        "Last Scrape": "2025-03-20 17:59"
    },
    {
        "Release Date": "1994-04",
        "Set": "Revised Edition",
        "Link": "https://www.tcgplayer.com/product/27365/Magic-Revised%20Edition-Revised%20Edition%20Booster%20Pack?xid=a4ebc4f68-ac2f-4c38-ac8a-7248e3eb545b&Language=English",
        "Current Price": "$314.99",
        "Bought At": "",
        "Owned": "FALSE",
        "Last Scrape": "2025-03-20 17:59"
    },
    {
        "Release Date": "1994-06",
        "Set": "Legends",
        "Link": "https://www.tcgplayer.com/product/27348/magic-legends-legends-booster-pack?Language=English&page=1",
        "Current Price": "$825.00",
        "Bought At": "",
        "Owned": "FALSE",
        "Last Scrape": "2025-03-20 17:59"
    },
    {
        "Release Date": "1994-08",
        "Set": "The Dark",
        "Link": "https://www.tcgplayer.com/product/27371/magic-the-dark-the-dark-booster-pack?Language=English&page=1",
        "Current Price": "$70.00",
        "Bought At": "",
        "Owned": "FALSE",
        "Last Scrape": "2025-03-20 18:12"
    },
    {
        "Release Date": "1994-11",
        "Set": "Fallen Empires",
        "Link": "https://www.tcgplayer.com/product/27338/Magic-Fallen%20Empires-Fallen%20Empires%20Booster%20Pack?xid=ac782965f-a658-460e-b2ee-79ab66d0e570&Language=English",
        "Current Price": "$14.86",
        "Bought At": "",
        "Owned": "FALSE",
        "Last Scrape": "2025-03-20 18:12"
    },
    {
        "Release Date": "1995-05",
        "Set": "Fourth Edition",
        "Link": "https://www.tcgplayer.com/product/27341/Magic-Fourth%20Edition-Fourth%20Edition%20Booster%20Pack?xid=a2451552f-c699-4a1e-99fb-224b54daf53a&Language=English",
        "Current Price": "$51.98",
        "Bought At": "",
        "Owned": "FALSE",
        "Last Scrape": "2025-03-20 18:12"
    },
    {
        "Release Date": "1995-06",
        "Set": "Ice Age",
        "Link": "https://www.tcgplayer.com/product/27345/Magic-Ice%20Age-Ice%20Age%20Booster%20Pack?xid=a22bbef3a-3d88-4dad-af1a-9110434c74a0&Language=English",
        "Current Price": "$40.00",
        "Bought At": "",
        "Owned": "FALSE",
        "Last Scrape": "2025-03-20 18:12"
    },
    {
        "Release Date": "1995-07",
        "Set": "Chronicles",
        "Link": "https://www.tcgplayer.com/product/214824/Magic-Double%20Masters-Double%20Masters%20Booster%20Pack?xid=ab5e32999-5366-42a7-8ff8-926324dc0587&Language=English",
        "Current Price": "$30.00",
        "Bought At": "",
        "Owned": "FALSE",
        "Last Scrape": "2025-03-20 18:12"
    },
    {
        "Release Date": "1995-10",
        "Set": "Homelands",
        "Link": "https://www.tcgplayer.com/product/27344/Magic-Homelands-Homelands%20Booster%20Pack?xid=ad5509993-f619-478f-9346-d78546c70fb8&Language=English",
        "Current Price": "$9.31",
        "Bought At": "",
        "Owned": "FALSE",
        "Last Scrape": "2025-03-20 18:12"
    },
    {
        "Release Date": "1996-06",
        "Set": "Alliances",
        "Link": "https://www.tcgplayer.com/product/27323/Magic-Alliances-Alliances%20Booster%20Pack?xid=a398090dd-4e73-4a86-990d-c5ba75268b56&Language=English",
        "Current Price": "$43.99",
        "Bought At": "",
        "Owned": "FALSE",
        "Last Scrape": "2025-03-20 17:59"
    },
    {
        "Release Date": "1996-10",
        "Set": "Mirage",
        "Link": "https://www.tcgplayer.com/product/27352/Magic-Mirage-Mirage%20Booster%20Pack?xid=a13203e4e-c37a-4fd9-8734-f0e529992862&Language=English",
        "Current Price": "$105.00",
        "Bought At": "",
        "Owned": "FALSE",
        "Last Scrape": "2025-03-20 17:59"
    },
    {
        "Release Date": "1997-02",
        "Set": "Visions",
        "Link": "https://www.tcgplayer.com/product/27379/Magic-Visions-Visions%20Booster%20Pack?xid=a8db5f794-f9b2-492f-86c7-04f2a919087a&Language=English",
        "Current Price": "$37.47",
        "Bought At": "",
        "Owned": "FALSE",
        "Last Scrape": "2025-03-20 17:59"
    },
    {
        "Release Date": "1997-03",
        "Set": "Fifth Edition",
        "Link": "https://www.tcgplayer.com/product/27340/Magic-Fifth%20Edition-Fifth%20Edition%20Booster%20Pack?xid=a1afce814-a439-4232-9878-bd0a96f944c1&Language=English",
        "Current Price": "$45.09",
        "Bought At": "",
        "Owned": "FALSE",
        "Last Scrape": "2025-03-20 17:59"
    },
    {
        "Release Date": "1997-05",
        "Set": "Portal",
        "Link": "https://www.tcgplayer.com/product/27360/Magic-Portal-Portal%20Booster%20Pack?xid=a1446aaa6-8f2e-4968-b126-63ea20e1a7a4&Language=English",
        "Current Price": "$28.65",
        "Bought At": "",
        "Owned": "FALSE",
        "Last Scrape": "2025-03-20 17:59"
    },
    {
        "Release Date": "1997-06",
        "Set": "Weatherlight",
        "Link": "https://www.tcgplayer.com/product/27380/Magic-Weatherlight-Weatherlight%20Booster%20Pack?xid=a7a34ce03-8d3e-434f-a12a-e232374d8bff&Language=English",
        "Current Price": "$28.04",
        "Bought At": "",
        "Owned": "FALSE",
        "Last Scrape": "2025-03-20 17:59"
    },
    {
        "Release Date": "1997-10",
        "Set": "Tempest",
        "Link": "https://www.tcgplayer.com/product/27370/Magic-Tempest-Tempest%20Booster%20Pack?xid=a38e71166-c5a3-44b2-bad2-69ffafac1a86&Language=English",
        "Current Price": "$70.00",
        "Bought At": "",
        "Owned": "FALSE",
        "Last Scrape": "2025-03-20 17:59"
    },
    {
        "Release Date": "1998-02",
        "Set": "Stronghold",
        "Link": "https://www.tcgplayer.com/product/27369/Magic-Stronghold-Stronghold%20Booster%20Pack?xid=ab3c2301d-6db9-414b-a547-b67ef967922b&Language=English",
        "Current Price": "$149.98",
        "Bought At": "",
        "Owned": "FALSE",
        "Last Scrape": "2025-03-20 17:59"
    },
    {
        "Release Date": "1998-06",
        "Set": "Exodus",
        "Link": "https://www.tcgplayer.com/product/27337/Magic-Exodus-Exodus%20Booster%20Pack?xid=ac4803634-689d-470a-8670-7ebf2fb2e773&Language=English",
        "Current Price": "$51.78",
        "Bought At": "",
        "Owned": "FALSE",
        "Last Scrape": "2025-03-20 17:59"
    },
    {
        "Release Date": "1998-06",
        "Set": "Portal Second Age",
        "Link": "https://www.tcgplayer.com/product/27361/Magic-Portal%20Second%20Age-Portal%20Second%20Age%20Booster%20Pack?xid=a5913ef05-37a8-40db-a0b5-951433c04207&Language=English",
        "Current Price": "$40.19",
        "Bought At": "",
        "Owned": "FALSE",
        "Last Scrape": "2025-03-20 17:59"
    },
    {
        "Release Date": "1998-08",
        "Set": "Unglued",
        "Link": "https://www.tcgplayer.com/product/27374/Magic-Unglued-Unglued%20Booster%20Pack?xid=a47ed6487-dac3-4886-aba1-579563b47eec&Language=English",
        "Current Price": "$42.78",
        "Bought At": "",
        "Owned": "FALSE",
        "Last Scrape": "2025-03-20 17:59"
    },
    {
        "Release Date": "1998-10",
        "Set": "Urza's Saga",
        "Link": "https://www.tcgplayer.com/product/27378/Magic-Urzas%20Saga-Urzas%20Saga%20Booster%20Pack?xid=a85c913a5-bc30-48d9-b16f-9d2e1992805b&Language=English",
        "Current Price": "$265.00",
        "Bought At": "",
        "Owned": "FALSE",
        "Last Scrape": "2025-03-20 17:59"
    },
    {
        "Release Date": "1999-02",
        "Set": "Urza's Legacy",
        "Link": "https://www.tcgplayer.com/product/27377/Magic-Urzas%20Legacy-Urzas%20Legacy%20Booster%20Pack?xid=a60a16be3-22d3-41e6-ab82-a461b514b5ee&Language=English",
        "Current Price": "$72.99",
        "Bought At": "",
        "Owned": "FALSE",
        "Last Scrape": "2025-03-20 17:59"
    },
    {
        "Release Date": "1999-04",
        "Set": "Sixth Edition",
        "Link": "https://www.tcgplayer.com/product/27332/Magic-Classic%20Sixth%20Edition-Classic%20Sixth%20Edition%20Booster%20Pack?xid=a9a13c396-da15-487f-8151-0f8d559e7912&Language=English",
        "Current Price": "$34.99",
        "Bought At": "",
        "Owned": "FALSE",
        "Last Scrape": "2025-03-20 17:59"
    },
    {
        "Release Date": "1999-05",
        "Set": "Portal Three Kingdoms",
        "Link": "https://www.tcgplayer.com/product/27362/Magic-Portal%20Three%20Kingdoms-Portal%20Three%20Kingdoms%20Booster%20Pack?xid=a45e02950-fc74-42b4-af00-e3812a471365&Language=English",
        "Current Price": "$422.49",
        "Bought At": "",
        "Owned": "FALSE",
        "Last Scrape": "2025-03-20 17:59"
    },
    {
        "Release Date": "1999-06",
        "Set": "Urza's Destiny",
        "Link": "https://www.tcgplayer.com/product/27376/Magic-Urzas%20Destiny-Urzas%20Destiny%20Booster%20Pack?xid=a280ef3bb-b305-4ac6-899b-4ab1c0841ad4&Language=English",
        "Current Price": "$78.43",
        "Bought At": "",
        "Owned": "FALSE",
        "Last Scrape": "2025-03-20 17:59"
    },
    {
        "Release Date": "1999-08",
        "Set": "Starter 1999",
        "Link": "https://www.tcgplayer.com/product/168359/magic-starter-1999-starter-1999-booster-pack?Language=English&page=1",
        "Current Price": "$34.79",
        "Bought At": "",
        "Owned": "FALSE",
        "Last Scrape": "2025-03-20 17:59"
    },
    {
        "Release Date": "1999-09",
        "Set": "Mercadian Masques",
        "Link": "https://www.tcgplayer.com/product/27351/Magic-Mercadian%20Masques-Mercadian%20Masques%20Booster%20Pack?xid=aa0f3c39f-0933-40b6-82e5-af79ed1b6f8d&Language=English",
        "Current Price": "$52.25",
        "Bought At": "",
        "Owned": "FALSE",
        "Last Scrape": "2025-03-20 17:59"
    },
    {
        "Release Date": "2000-02",
        "Set": "Nemesis",
        "Link": "https://www.tcgplayer.com/product/27355/Magic-Nemesis-Nemesis%20Booster%20Pack?xid=a19391a33-12cf-4348-a26b-910c625b3a78&Language=English",
        "Current Price": "$22.00",
        "Bought At": "",
        "Owned": "FALSE",
        "Last Scrape": "2025-03-20 17:59"
    },
    {
        "Release Date": "2000-04",
        "Set": "Starter 2000",
        "Link": "https://www.tcgplayer.com/product/257333/magic-starter-2000-starter-2000-sampler-booster-pack?Language=all",
        "Current Price": "",
        "Bought At": "",
        "Owned": "FALSE",
        "Last Scrape": ""
    },
    {
        "Release Date": "2000-06",
        "Set": "Prophecy",
        "Link": "https://www.tcgplayer.com/product/27363/Magic-Prophecy-Prophecy%20Booster%20Pack?xid=a95624bbb-b566-4f4f-aa3a-358bc4e447ad&Language=English",
        "Current Price": "$29.00",
        "Bought At": "",
        "Owned": "FALSE",
        "Last Scrape": "2025-03-20 17:59"
    },
    {
        "Release Date": "2000-09",
        "Set": "Invasion",
        "Link": "https://www.tcgplayer.com/product/27346/Magic-Invasion-Invasion%20Booster%20Pack?xid=a4a482017-6147-4116-b4e6-1313ac610365&Language=English",
        "Current Price": "$34.99",
        "Bought At": "",
        "Owned": "FALSE",
        "Last Scrape": "2025-03-20 17:59"
    },
    {
        "Release Date": "2001-01",
        "Set": "Planeshift",
        "Link": "https://www.tcgplayer.com/product/27359/Magic-Planeshift-Planeshift%20Booster%20Pack?xid=a0be53d57-94ab-453b-9cca-61e964056bb2&Language=English",
        "Current Price": "$35.00",
        "Bought At": "",
        "Owned": "FALSE",
        "Last Scrape": "2025-03-20 17:59"
    },
    {
        "Release Date": "2001-04",
        "Set": "Seventh Edition",
        "Link": "https://www.tcgplayer.com/product/27320/Magic-7th%20Edition-7th%20Edition%20Booster%20Pack?xid=a4fa53b83-9623-428a-a71c-659810c5f43e&Language=English",
        "Current Price": "$76.97",
        "Bought At": "",
        "Owned": "FALSE",
        "Last Scrape": "2025-03-20 17:59"
    },
    {
        "Release Date": "2001-05",
        "Set": "Apocalypse",
        "Link": "https://www.tcgplayer.com/product/27326/Magic-Apocalypse-Apocalypse%20Booster%20Pack?xid=aa3d1c81e-a0ca-4b7d-a711-c33e297dd57a&Language=English",
        "Current Price": "$27.10",
        "Bought At": "",
        "Owned": "FALSE",
        "Last Scrape": "2025-03-20 17:59"
    },
    {
        "Release Date": "2001-10",
        "Set": "Odyssey",
        "Link": "https://www.tcgplayer.com/product/27356/Magic-Odyssey-Odyssey%20Booster%20Pack?xid=aff63170a-ffa0-404a-851a-166c833fdfc8&Language=English",
        "Current Price": "$35.35",
        "Bought At": "",
        "Owned": "FALSE",
        "Last Scrape": "2025-03-20 17:59"
    },
    {
        "Release Date": "2002-02",
        "Set": "Torment",
        "Link": "https://www.tcgplayer.com/product/27373/Magic-Torment-Torment%20Booster%20Pack?xid=a9cf6fb9d-8447-43da-864b-e7e9b6b70b5e&Language=English",
        "Current Price": "$22.00",
        "Bought At": "",
        "Owned": "FALSE",
        "Last Scrape": "2025-03-20 17:59"
    },
    {
        "Release Date": "2002-05",
        "Set": "Judgment",
        "Link": "https://www.tcgplayer.com/product/27347/Magic-Judgment-Judgment%20Booster%20Pack?xid=abd339ee9-95e1-4e9c-a2af-f439f944da21&Language=English",
        "Current Price": "$24.99",
        "Bought At": "",
        "Owned": "FALSE",
        "Last Scrape": "2025-03-20 18:12"
    },
    {
        "Release Date": "2002-10",
        "Set": "Onslaught",
        "Link": "https://www.tcgplayer.com/product/27357/Magic-Onslaught-Onslaught%20Booster%20Pack?xid=a1968219b-69ca-4219-93b9-2f8ed3328e57&Language=English",
        "Current Price": "$50.00",
        "Bought At": "",
        "Owned": "FALSE",
        "Last Scrape": "2025-03-20 17:59"
    },
    {
        "Release Date": "2003-01",
        "Set": "Legions",
        "Link": "https://www.tcgplayer.com/product/27349/Magic-Legions-Legions%20Booster%20Pack?xid=a3e58858c-e3ed-44bb-9c32-6faf25905b96&Language=English",
        "Current Price": "$31.86",
        "Bought At": "",
        "Owned": "FALSE",
        "Last Scrape": "2025-03-20 17:59"
    },
    {
        "Release Date": "2003-05",
        "Set": "Scourge",
        "Link": "https://www.tcgplayer.com/product/27367/Magic-Scourge-Scourge%20Booster%20Pack?xid=a200423eb-5458-4fd2-b4ed-b94ed0c64280&Language=English",
        "Current Price": "$24.91",
        "Bought At": "",
        "Owned": "FALSE",
        "Last Scrape": "2025-03-20 17:59"
    },
    {
        "Release Date": "2003-07",
        "Set": "Eighth Edition",
        "Link": "https://www.tcgplayer.com/product/27321/Magic-8th%20Edition-8th%20Edition%20Booster%20Pack?xid=a974befde-fae5-419b-ab6b-d909dd519b99&Language=English",
        "Current Price": "$18.99",
        "Bought At": "",
        "Owned": "FALSE",
        "Last Scrape": "2025-03-20 17:59"
    },
    {
        "Release Date": "2003-10",
        "Set": "Mirrodin",
        "Link": "https://www.tcgplayer.com/product/27353/Magic-Mirrodin-Mirrodin%20Booster%20Pack?xid=addeeb1b4-d2f2-4278-ac81-37da8f33b6ed&Language=English",
        "Current Price": "$35.97",
        "Bought At": "",
        "Owned": "FALSE",
        "Last Scrape": "2025-03-20 17:59"
    },
    {
        "Release Date": "2004-02",
        "Set": "Darksteel",
        "Link": "https://www.tcgplayer.com/product/27334/Magic-Darksteel-Darksteel%20Booster%20Pack?xid=a6cd1b45b-e1e4-4d41-97c4-8f500831a029&Language=English",
        "Current Price": "$33.99",
        "Bought At": "",
        "Owned": "FALSE",
        "Last Scrape": "2025-03-20 17:59"
    },
    {
        "Release Date": "2004-06",
        "Set": "Fifth Dawn",
        "Link": "https://www.tcgplayer.com/product/27339/Magic-Fifth%20Dawn-Fifth%20Dawn%20Booster%20Pack?xid=aa7631742-7201-4070-bd4f-f81bdc702c8c&Language=English",
        "Current Price": "$27.73",
        "Bought At": "",
        "Owned": "FALSE",
        "Last Scrape": "2025-03-20 17:59"
    },
    {
        "Release Date": "2004-10",
        "Set": "Champions of Kamigawa",
        "Link": "https://www.tcgplayer.com/product/27330/Magic-Champions%20of%20Kamigawa-Champions%20of%20Kamigawa%20Booster%20Pack?xid=acca7c985-728d-4093-b048-0fad0379853e&Language=English",
        "Current Price": "$45.00",
        "Bought At": "",
        "Owned": "FALSE",
        "Last Scrape": "2025-03-20 17:59"
    },
    {
        "Release Date": "2004-11",
        "Set": "Unhinged",
        "Link": "https://www.tcgplayer.com/product/79291/Magic-Unhinged-Unhinged%20Booster%20Pack?xid=ade89def7-2c0f-4546-b839-70031bf6846c&Language=English",
        "Current Price": "$32.95",
        "Bought At": "",
        "Owned": "FALSE",
        "Last Scrape": "2025-03-20 17:59"
    },
    {
        "Release Date": "2005-02",
        "Set": "Betrayers of Kamigawa",
        "Link": "https://www.tcgplayer.com/product/27329/Magic-Betrayers%20of%20Kamigawa-Betrayers%20of%20Kamigawa%20Booster%20Pack?xid=a317f0e6a-4813-4b51-9b64-f1d39a344477&Language=English",
        "Current Price": "$23.78",
        "Bought At": "",
        "Owned": "FALSE",
        "Last Scrape": "2025-03-20 17:59"
    },
    {
        "Release Date": "2005-06",
        "Set": "Saviors of Kamigawa",
        "Link": "https://www.tcgplayer.com/product/27366/Magic-Saviors%20of%20Kamigawa-Saviors%20of%20Kamigawa%20Booster%20Pack?xid=a8f2adf27-a5a3-44c0-b636-d4234f1e61aa&Language=English",
        "Current Price": "$19.95",
        "Bought At": "",
        "Owned": "FALSE",
        "Last Scrape": "2025-03-20 17:59"
    },
    {
        "Release Date": "2005-07",
        "Set": "Ninth Edition",
        "Link": "https://www.tcgplayer.com/product/27322/Magic-9th%20Edition-9th%20Edition%20Booster%20Pack?xid=ad7d0ff28-f694-4ba5-9450-038ac38b98ef&Language=English",
        "Current Price": "$26.00",
        "Bought At": "",
        "Owned": "FALSE",
        "Last Scrape": "2025-03-20 17:59"
    },
    {
        "Release Date": "2005-10",
        "Set": "Ravnica: City of Guilds",
        "Link": "https://www.tcgplayer.com/product/27364/magic-ravnica-city-of-guilds-ravnica-booster-pack?Language=English&page=1",
        "Current Price": "$27.99",
        "Bought At": "",
        "Owned": "FALSE",
        "Last Scrape": "2025-03-20 17:59"
    },
    {
        "Release Date": "2006-02",
        "Set": "Guildpact",
        "Link": "https://www.tcgplayer.com/product/27343/magic-guildpact-guildpact-booster-pack?Language=English&page=1",
        "Current Price": "$21.19",
        "Bought At": "",
        "Owned": "FALSE",
        "Last Scrape": "2025-03-20 18:12"
    },
    {
        "Release Date": "2006-05",
        "Set": "Dissension",
        "Link": "https://www.tcgplayer.com/product/27335/magic-dissension-dissension-booster-pack?Language=English&page=1",
        "Current Price": "$17.90",
        "Bought At": "",
        "Owned": "FALSE",
        "Last Scrape": "2025-03-20 17:59"
    },
    {
        "Release Date": "2006-07",
        "Set": "Coldsnap",
        "Link": "https://www.tcgplayer.com/product/27333/magic-coldsnap-coldsnap-booster-pack?Language=English&page=1",
        "Current Price": "$23.99",
        "Bought At": "",
        "Owned": "FALSE",
        "Last Scrape": "2025-03-20 17:59"
    },
    {
        "Release Date": "2006-10",
        "Set": "Time Spiral",
        "Link": "https://www.tcgplayer.com/product/27372/magic-time-spiral-time-spiral-booster-pack?Language=English&page=1",
        "Current Price": "$47.99",
        "Bought At": "",
        "Owned": "FALSE",
        "Last Scrape": "2025-03-20 17:59"
    },
    {
        "Release Date": "2007-02",
        "Set": "Planar Chaos",
        "Link": "https://www.tcgplayer.com/product/27358/magic-planar-chaos-planar-chaos-booster-pack?Language=English&page=1",
        "Current Price": "$24.99",
        "Bought At": "",
        "Owned": "FALSE",
        "Last Scrape": "2025-03-20 17:59"
    },
    {
        "Release Date": "2007-05",
        "Set": "Future Sight",
        "Link": "https://www.tcgplayer.com/product/27342/magic-future-sight-future-sight-booster-pack?Language=English&page=1",
        "Current Price": "$34.00",
        "Bought At": "",
        "Owned": "FALSE",
        "Last Scrape": "2025-03-20 17:59"
    },
    {
        "Release Date": "2007-07",
        "Set": "Tenth Edition",
        "Link": "https://www.tcgplayer.com/product/27319/magic-10th-edition-10th-edition-booster-pack?Language=English&page=1",
        "Current Price": "$29.99",
        "Bought At": "",
        "Owned": "FALSE",
        "Last Scrape": "2025-03-20 17:59"
    },
    {
        "Release Date": "2007-10",
        "Set": "Lorwyn",
        "Link": "https://www.tcgplayer.com/product/27350/magic-lorwyn-lorwyn-booster-pack?Language=English&page=1",
        "Current Price": "$38.09",
        "Bought At": "",
        "Owned": "FALSE",
        "Last Scrape": "2025-03-20 17:59"
    },
    {
        "Release Date": "2008-02",
        "Set": "Morningtide",
        "Link": "https://www.tcgplayer.com/product/27354/magic-morningtide-morningtide-booster-pack?Language=English&page=1",
        "Current Price": "$19.99",
        "Bought At": "",
        "Owned": "FALSE",
        "Last Scrape": "2025-03-20 17:59"
    },
    {
        "Release Date": "2008-05",
        "Set": "Shadowmoor",
        "Link": "https://www.tcgplayer.com/product/27368/magic-shadowmoor-shadowmoor-booster-pack?Language=English&page=1",
        "Current Price": "$56.34",
        "Bought At": "",
        "Owned": "FALSE",
        "Last Scrape": "2025-03-20 17:59"
    },
    {
        "Release Date": "2008-06",
        "Set": "Eventide",
        "Link": "https://www.tcgplayer.com/product/27336/magic-eventide-eventide-booster-pack?Language=English&page=1",
        "Current Price": "$19.99",
        "Bought At": "",
        "Owned": "FALSE",
        "Last Scrape": "2025-03-20 17:59"
    },
    {
        "Release Date": "2008-10",
        "Set": "Shards of Alara",
        "Link": "https://www.tcgplayer.com/product/28639/magic-shards-of-alara-shards-of-alara-booster-pack?Language=English&page=1",
        "Current Price": "$23.98",
        "Bought At": "",
        "Owned": "FALSE",
        "Last Scrape": "2025-03-20 17:59"
    },
    {
        "Release Date": "2009-02",
        "Set": "Conflux",
        "Link": "https://www.tcgplayer.com/product/108337/magic-conflux-conflux-booster-pack?Language=English&page=1",
        "Current Price": "$18.97",
        "Bought At": "",
        "Owned": "FALSE",
        "Last Scrape": "2025-03-20 17:59"
    },
    {
        "Release Date": "2009-04",
        "Set": "Alara Reborn",
        "Link": "https://www.tcgplayer.com/product/31840/magic-alara-reborn-alara-reborn-booster-pack?Language=English&page=1",
        "Current Price": "$18.95",
        "Bought At": "",
        "Owned": "FALSE",
        "Last Scrape": "2025-03-20 17:59"
    },
    {
        "Release Date": "2009-07",
        "Set": "Magic 2010",
        "Link": "https://www.tcgplayer.com/product/32530/magic-magic-2010-m10-magic-2010-m10-booster-pack?Language=English&page=1",
        "Current Price": "$14.55",
        "Bought At": "",
        "Owned": "FALSE",
        "Last Scrape": "2025-03-20 17:59"
    },
    {
        "Release Date": "2009-10",
        "Set": "Zendikar",
        "Link": "https://www.tcgplayer.com/product/32791/magic-zendikar-zendikar-booster-pack?Language=English&page=1",
        "Current Price": "$34.52",
        "Bought At": "",
        "Owned": "FALSE",
        "Last Scrape": "2025-03-20 17:59"
    },
    {
        "Release Date": "2010-02",
        "Set": "Worldwake",
        "Link": "https://www.tcgplayer.com/product/34469/magic-worldwake-worldwake-booster-pack?Language=English&page=1",
        "Current Price": "$39.95",
        "Bought At": "",
        "Owned": "FALSE",
        "Last Scrape": "2025-03-20 18:12"
    },
    {
        "Release Date": "2010-04",
        "Set": "Rise of the Eldrazi",
        "Link": "https://www.tcgplayer.com/product/34680/magic-rise-of-the-eldrazi-rise-of-the-eldrazi-booster-pack?Language=English&page=1",
        "Current Price": "$49.99",
        "Bought At": "",
        "Owned": "FALSE",
        "Last Scrape": "2025-03-20 17:59"
    },
    {
        "Release Date": "2010-07",
        "Set": "Magic 2011",
        "Link": "https://www.tcgplayer.com/product/35374/magic-magic-2011-m11-magic-2011-m11-booster-pack?Language=English&page=1",
        "Current Price": "$11.27",
        "Bought At": "",
        "Owned": "FALSE",
        "Last Scrape": "2025-03-20 17:59"
    },
    {
        "Release Date": "2010-10",
        "Set": "Scars of Mirrodin",
        "Link": "https://www.tcgplayer.com/product/35747/magic-scars-of-mirrodin-scars-of-mirrodin-booster-pack?Language=English&page=1",
        "Current Price": "$18.68",
        "Bought At": "",
        "Owned": "FALSE",
        "Last Scrape": "2025-03-20 17:59"
    },
    {
        "Release Date": "2011-02",
        "Set": "Mirrodin Besieged (Regular)",
        "Link": "https://www.tcgplayer.com/product/39108/magic-mirrodin-besieged-mirrodin-besieged-booster-pack?Language=English&page=1",
        "Current Price": "$15.00",
        "Bought At": "",
        "Owned": "FALSE",
        "Last Scrape": "2025-03-20 17:59"
    },
    {
        "Release Date": "2011-02",
        "Set": "Mirrodin Besieged (Phyrexian Faction)",
        "Link": "https://www.tcgplayer.com/product/72026/magic-mirrodin-besieged-mirrodin-besieged-phyrexian-faction-booster-pack?Language=English&page=1",
        "Current Price": "$22.97",
        "Bought At": "",
        "Owned": "FALSE",
        "Last Scrape": "2025-03-20 17:59"
    },
    {
        "Release Date": "2011-02",
        "Set": "Mirrodin Besieged (Mirran Faction)",
        "Link": "https://www.tcgplayer.com/product/72025/magic-mirrodin-besieged-mirrodin-besieged-mirran-faction-booster-pack?Language=English&page=1",
        "Current Price": "$17.95",
        "Bought At": "",
        "Owned": "FALSE",
        "Last Scrape": "2025-03-20 17:59"
    },
    {
        "Release Date": "2011-05",
        "Set": "New Phyrexia",
        "Link": "https://www.tcgplayer.com/product/39409/magic-new-phyrexia-new-phyrexia-booster-pack?Language=English&page=1",
        "Current Price": "$34.99",
        "Bought At": "",
        "Owned": "FALSE",
        "Last Scrape": "2025-03-20 17:59"
    },
    {
        "Release Date": "2011-07",
        "Set": "Magic 2012",
        "Link": "https://www.tcgplayer.com/product/46956/magic-magic-2012-m12-magic-2012-m12-booster-pack?Language=English&page=1",
        "Current Price": "$8.99",
        "Bought At": "",
        "Owned": "FALSE",
        "Last Scrape": "2025-03-20 17:59"
    },
    {
        "Release Date": "2011-09",
        "Set": "Innistrad",
        "Link": "https://www.tcgplayer.com/product/47787/magic-innistrad-innistrad-booster-pack?Language=English&page=1",
        "Current Price": "$19.19",
        "Bought At": "",
        "Owned": "FALSE",
        "Last Scrape": "2025-03-20 17:59"
    },
    {
        "Release Date": "2012-02",
        "Set": "Dark Ascension",
        "Link": "https://www.tcgplayer.com/product/57583/magic-dark-ascension-dark-ascension-booster-pack?Language=English&Condition=Unopened&page=1",
        "Current Price": "$6.93",
        "Bought At": "",
        "Owned": "FALSE",
        "Last Scrape": "2025-03-20 17:59"
    },
    {
        "Release Date": "2012-05",
        "Set": "Avacyn Restored",
        "Link": "https://www.tcgplayer.com/product/58056/magic-avacyn-restored-avacyn-restored-booster-pack?Language=English&Condition=Unopened&page=1",
        "Current Price": "$18.89",
        "Bought At": "",
        "Owned": "FALSE",
        "Last Scrape": "2025-03-20 17:59"
    },
    {
        "Release Date": "2012-07",
        "Set": "Magic 2013",
        "Link": "https://www.tcgplayer.com/product/59123/magic-magic-2013-m13-magic-2013-m13-booster-pack?Language=English&Condition=Unopened&page=1",
        "Current Price": "$9.28",
        "Bought At": "",
        "Owned": "FALSE",
        "Last Scrape": "2025-03-20 17:59"
    },
    {
        "Release Date": "2012-10",
        "Set": "Return to Ravnica",
        "Link": "https://www.tcgplayer.com/product/60121/magic-return-to-ravnica-return-to-ravnica-booster-pack?Language=English&Condition=Unopened&page=1",
        "Current Price": "$5.99",
        "Bought At": "$5.00",
        "Owned": "TRUE",
        "Last Scrape": "2025-03-20 17:59"
    },
    {
        "Release Date": "2013-02",
        "Set": "Gatecrash",
        "Link": "https://www.tcgplayer.com/product/67313/magic-gatecrash-gatecrash-booster-pack?Language=English&Condition=Unopened&page=1",
        "Current Price": "$6.03",
        "Bought At": "$6.03",
        "Owned": "TRUE",
        "Last Scrape": "2025-03-20 17:59"
    },
    {
        "Release Date": "2013-05",
        "Set": "Dragon's Maze",
        "Link": "https://www.tcgplayer.com/product/67752/magic-dragons-maze-dragons-maze-booster-pack?Language=English&Condition=Unopened&page=1",
        "Current Price": "$5.90",
        "Bought At": "$5.90",
        "Owned": "TRUE",
        "Last Scrape": "2025-03-20 17:59"
    },
    {
        "Release Date": "2013-06",
        "Set": "Modern Masters",
        "Link": "https://www.tcgplayer.com/product/68105/magic-modern-masters-modern-masters-booster-pack?Language=English&page=1",
        "Current Price": "$18.88",
        "Bought At": "",
        "Owned": "FALSE",
        "Last Scrape": "2025-03-20 17:59"
    },
    {
        "Release Date": "2013-07",
        "Set": "Magic 2014",
        "Link": "https://www.tcgplayer.com/product/78289/magic-magic-2014-m14-magic-2014-booster-battle-pack?Language=English&page=1",
        "Current Price": "$22.96",
        "Bought At": "",
        "Owned": "FALSE",
        "Last Scrape": "2025-03-20 18:12"
    },
    {
        "Release Date": "2013-09",
        "Set": "Theros",
        "Link": "https://www.tcgplayer.com/product/70961/magic-theros-theros-booster-pack?Language=English&page=1",
        "Current Price": "$8.99",
        "Bought At": "",
        "Owned": "FALSE",
        "Last Scrape": "2025-03-20 18:12"
    },
    {
        "Release Date": "2014-02",
        "Set": "Born of the Gods",
        "Link": "https://www.tcgplayer.com/product/77982/magic-born-of-the-gods-born-of-the-gods-booster-pack?Language=English&page=1",
        "Current Price": "$5.44",
        "Bought At": "",
        "Owned": "FALSE",
        "Last Scrape": "2025-03-20 18:12"
    },
    {
        "Release Date": "2014-05",
        "Set": "Journey into Nyx",
        "Link": "https://www.tcgplayer.com/product/80839/magic-journey-into-nyx-journey-into-nyx-booster-pack?Language=English&page=1",
        "Current Price": "$5.56",
        "Bought At": "",
        "Owned": "FALSE",
        "Last Scrape": "2025-03-20 18:12"
    },
    {
        "Release Date": "2014-07",
        "Set": "Magic 2015",
        "Link": "https://www.tcgplayer.com/product/90785/magic-magic-2015-m15-magic-2015-m15-booster-pack?Language=English&page=1",
        "Current Price": "$6.97",
        "Bought At": "",
        "Owned": "FALSE",
        "Last Scrape": "2025-03-20 18:12"
    },
    {
        "Release Date": "2014-10",
        "Set": "Khans of Tarkir",
        "Link": "https://www.tcgplayer.com/product/91653/magic-khans-of-tarkir-khans-of-tarkir-booster-pack?Language=English&page=1",
        "Current Price": "$7.85",
        "Bought At": "",
        "Owned": "FALSE",
        "Last Scrape": "2025-03-20 17:59"
    },
    {
        "Release Date": "2015-01",
        "Set": "Fate Reforged",
        "Link": "https://www.tcgplayer.com/product/95031/magic-fate-reforged-fate-reforged-booster-pack?Language=English&page=1",
        "Current Price": "$8.11",
        "Bought At": "",
        "Owned": "FALSE",
        "Last Scrape": "2025-03-20 17:59"
    },
    {
        "Release Date": "2015-03",
        "Set": "Dragons of Tarkir",
        "Link": "https://www.tcgplayer.com/product/96139/magic-dragons-of-tarkir-dragons-of-tarkir-booster-pack?Language=English&page=1",
        "Current Price": "$9.97",
        "Bought At": "",
        "Owned": "FALSE",
        "Last Scrape": "2025-03-20 17:59"
    },
    {
        "Release Date": "2015-05",
        "Set": "Modern Masters 2015",
        "Link": "https://www.tcgplayer.com/product/95053/magic-modern-masters-2015-modern-masters-2015-booster-pack?Language=English&page=1",
        "Current Price": "$17.49",
        "Bought At": "",
        "Owned": "FALSE",
        "Last Scrape": "2025-03-20 17:59"
    },
    {
        "Release Date": "2015-07",
        "Set": "Magic Origins",
        "Link": "https://www.tcgplayer.com/product/96148/magic-magic-origins-magic-origins-booster-pack?Language=English&page=1",
        "Current Price": "$4.50",
        "Bought At": "",
        "Owned": "FALSE",
        "Last Scrape": "2025-03-20 17:59"
    },
    {
        "Release Date": "2015-10",
        "Set": "Battle for Zendikar",
        "Link": "https://www.tcgplayer.com/product/102716/magic-battle-for-zendikar-battle-for-zendikar-booster-pack?Language=English&page=1",
        "Current Price": "$5.99",
        "Bought At": "",
        "Owned": "FALSE",
        "Last Scrape": "2025-03-20 17:59"
    },
    {
        "Release Date": "2016-01",
        "Set": "Oath of the Gatewatch",
        "Link": "https://www.tcgplayer.com/product/110420/magic-oath-of-the-gatewatch-oath-of-the-gatewatch-booster-pack?Language=English&page=1",
        "Current Price": "$4.99",
        "Bought At": "",
        "Owned": "FALSE",
        "Last Scrape": "2025-03-20 17:59"
    },
    {
        "Release Date": "2016-04",
        "Set": "Shadows over Innistrad",
        "Link": "https://www.tcgplayer.com/product/112708/magic-shadows-over-innistrad-shadows-over-innistrad-booster-pack?Language=English&page=1",
        "Current Price": "$7.24",
        "Bought At": "",
        "Owned": "FALSE",
        "Last Scrape": "2025-03-20 18:12"
    },
    {
        "Release Date": "2016-06",
        "Set": "Eternal Masters",
        "Link": "https://www.tcgplayer.com/product/114833/Magic-Eternal%20Masters-Eternal%20Masters%20Booster%20Pack?xid=a3946b31f-47cf-400f-9d55-508e8ad388a1&Language=English",
        "Current Price": "$19.99",
        "Bought At": "",
        "Owned": "FALSE",
        "Last Scrape": "2025-03-20 18:12"
    },
    {
        "Release Date": "2016-07",
        "Set": "Eldritch Moon",
        "Link": "https://www.tcgplayer.com/product/114833/magic-eternal-masters-eternal-masters-booster-pack?Language=English&page=1",
        "Current Price": "$19.99",
        "Bought At": "",
        "Owned": "FALSE",
        "Last Scrape": "2025-03-20 18:12"
    },
    {
        "Release Date": "2016-09",
        "Set": "Kaladesh",
        "Link": "https://www.tcgplayer.com/product/121529/magic-kaladesh-kaladesh-booster-pack?Language=English&page=1",
        "Current Price": "$15.80",
        "Bought At": "",
        "Owned": "FALSE",
        "Last Scrape": "2025-03-20 18:12"
    },
    {
        "Release Date": "2017-01",
        "Set": "Aether Revolt",
        "Link": "https://www.tcgplayer.com/product/125793/magic-aether-revolt-aether-revolt-booster-pack?Language=English&page=1",
        "Current Price": "$5.75",
        "Bought At": "",
        "Owned": "FALSE",
        "Last Scrape": "2025-03-20 18:12"
    },
    {
        "Release Date": "2017-03",
        "Set": "Modern Masters 2017",
        "Link": "https://www.tcgplayer.com/product/127068/Magic-Modern%20Masters%202017-Modern%20Masters%202017%20Booster%20Pack?xid=ac1680b04-8c0e-4a81-b982-c4de21b58a90&Language=English",
        "Current Price": "$19.07",
        "Bought At": "",
        "Owned": "FALSE",
        "Last Scrape": "2025-03-20 18:12"
    },
    {
        "Release Date": "2017-04",
        "Set": "Amonkhet",
        "Link": "https://www.tcgplayer.com/product/127173/magic-amonkhet-amonkhet-booster-pack?Language=English&page=1",
        "Current Price": "$10.97",
        "Bought At": "",
        "Owned": "FALSE",
        "Last Scrape": "2025-03-20 18:12"
    },
    {
        "Release Date": "2017-07",
        "Set": "Hour of Devastation",
        "Link": "https://www.tcgplayer.com/product/131457/magic-hour-of-devastation-hour-of-devastation-booster-pack?Language=English&page=1",
        "Current Price": "$7.92",
        "Bought At": "",
        "Owned": "FALSE",
        "Last Scrape": "2025-03-20 18:12"
    },
    {
        "Release Date": "2017-09",
        "Set": "Ixalan",
        "Link": "https://www.tcgplayer.com/product/141991/magic-ixalan-ixalan-booster-pack?Language=English&page=1",
        "Current Price": "$5.52",
        "Bought At": "",
        "Owned": "FALSE",
        "Last Scrape": "2025-03-20 18:12"
    },
    {
        "Release Date": "2017-11",
        "Set": "Iconic Masters",
        "Link": "https://www.tcgplayer.com/product/145236/Magic-Iconic%20Masters-Iconic%20Masters%20Booster%20Pack?xid=ab4eaad64-fa2a-4c35-8c34-02ac6217181c&Language=English",
        "Current Price": "$10.49",
        "Bought At": "",
        "Owned": "FALSE",
        "Last Scrape": "2025-03-20 18:12"
    },
    {
        "Release Date": "2017-12",
        "Set": "Unstable",
        "Link": "https://www.tcgplayer.com/product/149403/magic-unstable-unstable-booster-pack?Language=English&page=1",
        "Current Price": "$7.40",
        "Bought At": "",
        "Owned": "FALSE",
        "Last Scrape": "2025-03-20 18:12"
    },
    {
        "Release Date": "2018-01",
        "Set": "Rivals of Ixalan",
        "Link": "https://www.tcgplayer.com/product/149405/magic-rivals-of-ixalan-rivals-of-ixalan-booster-pack?Language=English&page=1",
        "Current Price": "$6.15",
        "Bought At": "",
        "Owned": "FALSE",
        "Last Scrape": "2025-03-20 18:12"
    },
    {
        "Release Date": "2018-03",
        "Set": "Masters 25",
        "Link": "https://www.tcgplayer.com/product/157861/Magic-Masters%2025-Masters%2025%20Booster%20Pack?xid=ad5892c24-90bc-42e7-b10f-da8794e73b84&Language=English",
        "Current Price": "$13.44",
        "Bought At": "",
        "Owned": "FALSE",
        "Last Scrape": "2025-03-20 18:12"
    },
    {
        "Release Date": "2018-04",
        "Set": "Dominaria",
        "Link": "https://www.tcgplayer.com/product/158425/magic-dominaria-dominaria-booster-pack?Language=English&page=1",
        "Current Price": "$4.98",
        "Bought At": "",
        "Owned": "FALSE",
        "Last Scrape": "2025-03-20 18:12"
    },
    {
        "Release Date": "2018-06",
        "Set": "Battlebond",
        "Link": "https://www.tcgplayer.com/product/166538/magic-battlebond-battlebond-booster-pack?Language=English&page=1",
        "Current Price": "$9.16",
        "Bought At": "",
        "Owned": "FALSE",
        "Last Scrape": "2025-03-20 18:12"
    },
    {
        "Release Date": "2018-07",
        "Set": "Core Set 2019",
        "Link": "https://www.tcgplayer.com/product/166551/magic-core-set-2019-core-set-2019-booster-pack?Language=English&page=1",
        "Current Price": "$4.99",
        "Bought At": "",
        "Owned": "FALSE",
        "Last Scrape": "2025-03-20 18:12"
    },
    {
        "Release Date": "2018-10",
        "Set": "Guilds of Ravnica",
        "Link": "https://www.tcgplayer.com/product/173364/magic-guilds-of-ravnica-guilds-of-ravnica-booster-pack?Language=English&page=1",
        "Current Price": "$4.93",
        "Bought At": "",
        "Owned": "FALSE",
        "Last Scrape": "2025-03-20 18:12"
    },
    {
        "Release Date": "2018-10",
        "Set": "Guilds of Ravnica (Theme)",
        "Link": "https://www.tcgplayer.com/product/176703/magic-guilds-of-ravnica-guilds-of-ravnica-theme-booster-pack-set-of-5?Language=English&page=1",
        "Current Price": "$50.97",
        "Bought At": "",
        "Owned": "FALSE",
        "Last Scrape": "2025-03-20 18:12"
    },
    {
        "Release Date": "2018-12",
        "Set": "Ultimate Masters",
        "Link": "https://www.tcgplayer.com/product/179445/Magic-Ultimate%20Masters-Ultimate%20Masters%20Booster%20Pack?xid=a6c92c989-1d79-4a02-9456-3d7fcf1dafa4&Language=English",
        "Current Price": "$19.20",
        "Bought At": "",
        "Owned": "FALSE",
        "Last Scrape": "2025-03-20 18:12"
    },
    {
        "Release Date": "2019-01",
        "Set": "Ravnica Allegiance (Booster)",
        "Link": "https://www.tcgplayer.com/product/180735/magic-ravnica-allegiance-ravnica-allegiance-booster-pack?Language=English&page=1",
        "Current Price": "$4.28",
        "Bought At": "",
        "Owned": "FALSE",
        "Last Scrape": "2025-03-20 18:12"
    },
    {
        "Release Date": "2019-01",
        "Set": "Ravnica Allegiance (Theme)",
        "Link": "https://www.tcgplayer.com/product/183323/magic-ravnica-allegiance-ravnica-allegiance-theme-booster-pack-set-of-5?Language=English&page=1",
        "Current Price": "",
        "Bought At": "",
        "Owned": "FALSE",
        "Last Scrape": ""
    },
    {
        "Release Date": "2019-01",
        "Set": "Ravnica Allegiance (Collectors)",
        "Link": "https://www.tcgplayer.com/product/184538/magic-ravnica-allegiance-ravnica-allegiance-collectors-booster-pack?Language=English&page=1",
        "Current Price": "",
        "Bought At": "",
        "Owned": "FALSE",
        "Last Scrape": ""
    },
    {
        "Release Date": "2019-05",
        "Set": "War of the Spark",
        "Link": "https://www.tcgplayer.com/product/185677/magic-war-of-the-spark-war-of-the-spark-booster-pack?Language=English&page=1",
        "Current Price": "$4.95",
        "Bought At": "",
        "Owned": "FALSE",
        "Last Scrape": "2025-03-20 18:12"
    },
    {
        "Release Date": "2019-05",
        "Set": "War of the Spark (Theme)",
        "Link": "https://www.tcgplayer.com/product/188644/magic-war-of-the-spark-war-of-the-spark-theme-booster-pack-set-of-5?Language=English&page=1",
        "Current Price": "$24.99",
        "Bought At": "",
        "Owned": "FALSE",
        "Last Scrape": "2025-03-20 18:12"
    },
    {
        "Release Date": "2019-06",
        "Set": "Modern Horizons",
        "Link": "https://www.tcgplayer.com/product/185892/magic-modern-horizons-modern-horizons-booster-pack?Language=English&page=1",
        "Current Price": "$6.50",
        "Bought At": "",
        "Owned": "FALSE",
        "Last Scrape": "2025-03-20 18:12"
    },
    {
        "Release Date": "2019-07",
        "Set": "Core Set 2020 (Theme)",
        "Link": "https://www.tcgplayer.com/product/192769/magic-core-set-2020-core-set-2020-theme-booster-set-of-5?Language=English&page=1",
        "Current Price": "$24.99",
        "Bought At": "",
        "Owned": "FALSE",
        "Last Scrape": "2025-03-20 18:12"
    },
    {
        "Release Date": "2019-07",
        "Set": "Core Set 2020",
        "Link": "https://www.tcgplayer.com/product/188211/magic-core-set-2020-core-set-2020-booster-pack?Language=English&page=1",
        "Current Price": "$5.25",
        "Bought At": "",
        "Owned": "FALSE",
        "Last Scrape": "2025-03-20 18:12"
    },
    {
        "Release Date": "2019-10",
        "Set": "Throne of Eldraine (Draft)",
        "Link": "https://www.tcgplayer.com/product/194892/magic-throne-of-eldraine-throne-of-eldraine-draft-booster-pack?Language=English&page=1",
        "Current Price": "$4.00",
        "Bought At": "",
        "Owned": "FALSE",
        "Last Scrape": "2025-03-20 18:12"
    },
    {
        "Release Date": "2019-10",
        "Set": "Throne of Eldraine (Theme)",
        "Link": "https://www.tcgplayer.com/product/194905/magic-throne-of-eldraine-throne-of-eldraine-theme-booster-pack-set-of-5?Language=English&page=1",
        "Current Price": "$50.00",
        "Bought At": "",
        "Owned": "FALSE",
        "Last Scrape": "2025-03-20 18:12"
    },
    {
        "Release Date": "2019-10",
        "Set": "Throne of Eldraine (Collectors)",
        "Link": "https://www.tcgplayer.com/product/194906/magic-throne-of-eldraine-throne-of-eldraine-collector-booster-pack?Language=English&page=1",
        "Current Price": "$26.99",
        "Bought At": "",
        "Owned": "FALSE",
        "Last Scrape": "2025-03-20 18:12"
    },
    {
        "Release Date": "2019-11",
        "Set": "Mystery Booster",
        "Link": "https://www.tcgplayer.com/product/202644/magic-mystery-booster-convention-edition-exclusives-mystery-booster-booster-pack-convention-edition-2019?Language=English&page=1",
        "Current Price": "$22.75",
        "Bought At": "",
        "Owned": "FALSE",
        "Last Scrape": "2025-03-20 18:12"
    },
    {
        "Release Date": "2020-01",
        "Set": "Theros Beyond Death",
        "Link": "https://www.tcgplayer.com/product/202299/magic-theros-beyond-death-theros-beyond-death-booster-pack?Language=English&page=1",
        "Current Price": "$6.27",
        "Bought At": "",
        "Owned": "FALSE",
        "Last Scrape": "2025-03-20 18:12"
    },
    {
        "Release Date": "2020-01",
        "Set": "Theros Beyond Death (Theme)",
        "Link": "https://www.tcgplayer.com/product/206263/magic-theros-beyond-death-theros-beyond-death-theme-booster-pack-set-of-5?Language=English&page=1",
        "Current Price": "$53.99",
        "Bought At": "",
        "Owned": "FALSE",
        "Last Scrape": "2025-03-20 18:12"
    },
    {
        "Release Date": "2020-01",
        "Set": "Theros Beyond Death (Collectors)",
        "Link": "https://www.tcgplayer.com/product/206254/magic-theros-beyond-death-theros-beyond-death-collector-booster-pack?Language=English&page=1",
        "Current Price": "$24.48",
        "Bought At": "",
        "Owned": "FALSE",
        "Last Scrape": "2025-03-20 18:12"
    },
    {
        "Release Date": "2020-03",
        "Set": "Mystery Booster Retail Edition",
        "Link": "https://www.tcgplayer.com/product/202647/magic-mystery-booster-retail-exclusives-mystery-booster-booster-pack-retail-exclusive?Language=English&page=1",
        "Current Price": "$20.69",
        "Bought At": "",
        "Owned": "FALSE",
        "Last Scrape": "2025-03-20 18:12"
    },
    {
        "Release Date": "2020-04",
        "Set": "Ikoria: Lair of Behemoths",
        "Link": "https://www.tcgplayer.com/product/208277/magic-ikoria-lair-of-behemoths-ikoria-lair-of-behemoths-booster-pack?Language=English&page=1",
        "Current Price": "$6.31",
        "Bought At": "",
        "Owned": "FALSE",
        "Last Scrape": "2025-03-20 18:12"
    },
    {
        "Release Date": "2020-04",
        "Set": "Ikoria: Lair of Behemoths (Theme)",
        "Link": "https://www.tcgplayer.com/product/208283/magic-ikoria-lair-of-behemoths-ikoria-lair-of-behemoths-theme-booster-set-of-6?Language=English&page=1",
        "Current Price": "$54.99",
        "Bought At": "",
        "Owned": "FALSE",
        "Last Scrape": "2025-03-20 18:12"
    },
    {
        "Release Date": "2020-04",
        "Set": "Ikoria: Lair of Behemoths (Collectors)",
        "Link": "https://www.tcgplayer.com/product/208280/magic-ikoria-lair-of-behemoths-ikoria-lair-of-behemoths-collector-booster-pack?Language=English&page=1",
        "Current Price": "$29.84",
        "Bought At": "",
        "Owned": "FALSE",
        "Last Scrape": "2025-03-20 18:12"
    },
    {
        "Release Date": "2020-07",
        "Set": "Core Set 2021",
        "Link": "https://www.tcgplayer.com/product/214813/magic-core-set-2021-core-set-2021-booster-pack?Language=English&page=1",
        "Current Price": "$4.40",
        "Bought At": "",
        "Owned": "FALSE",
        "Last Scrape": "2025-03-20 18:12"
    },
    {
        "Release Date": "2020-07",
        "Set": "Core Set 2021 (Collectors)",
        "Link": "https://www.tcgplayer.com/product/215325/magic-core-set-2021-core-set-2021-collector-booster-pack?Language=English&page=1",
        "Current Price": "$25.37",
        "Bought At": "",
        "Owned": "FALSE",
        "Last Scrape": "2025-03-20 18:12"
    },
    {
        "Release Date": "2020-07",
        "Set": "Jumpstart",
        "Link": "https://www.tcgplayer.com/product/214822/magic-jumpstart-jumpstart-booster-pack?Language=English&page=1",
        "Current Price": "$6.24",
        "Bought At": "",
        "Owned": "FALSE",
        "Last Scrape": "2025-03-20 18:12"
    },
    {
        "Release Date": "2020-08",
        "Set": "Double Masters",
        "Link": "https://www.tcgplayer.com/product/214824/Magic-Double%20Masters-Double%20Masters%20Booster%20Pack?xid=a08dc1155-3fae-4d51-889d-db87e296ad44&Language=English",
        "Current Price": "$30.00",
        "Bought At": "",
        "Owned": "FALSE",
        "Last Scrape": "2025-03-20 18:12"
    },
    {
        "Release Date": "2020-09",
        "Set": "Zendikar Rising (Set )",
        "Link": "https://www.tcgplayer.com/product/220524/magic-zendikar-rising-zendikar-rising-set-booster-pack?Language=English&page=1",
        "Current Price": "$4.85",
        "Bought At": "",
        "Owned": "FALSE",
        "Last Scrape": "2025-03-20 18:12"
    },
    {
        "Release Date": "2020-09",
        "Set": "Zendikar Rising (Draft)",
        "Link": "https://www.tcgplayer.com/product/220413/magic-zendikar-rising-zendikar-rising-draft-booster-pack?Language=English&page=1",
        "Current Price": "$3.98",
        "Bought At": "",
        "Owned": "FALSE",
        "Last Scrape": "2025-03-20 18:12"
    },
    {
        "Release Date": "2020-09",
        "Set": "Zendikar Rising (Theme)",
        "Link": "https://www.tcgplayer.com/product/222008/magic-zendikar-rising-zendikar-rising-theme-booster-set-of-6?Language=English&page=1",
        "Current Price": "$39.27",
        "Bought At": "",
        "Owned": "FALSE",
        "Last Scrape": "2025-03-20 18:12"
    },
    {
        "Release Date": "2020-09",
        "Set": "Zendikar Rising (Collectors)",
        "Link": "https://www.tcgplayer.com/product/220422/magic-zendikar-rising-zendikar-rising-collector-booster-pack?Language=English&page=1",
        "Current Price": "$19.00",
        "Bought At": "",
        "Owned": "FALSE",
        "Last Scrape": "2025-03-20 18:12"
    },
    {
        "Release Date": "2020-11",
        "Set": "Commander Legends (Draft)",
        "Link": "https://www.tcgplayer.com/product/221318/magic-commander-legends-commander-legends-draft-booster-pack?Language=English&page=1",
        "Current Price": "$7.29",
        "Bought At": "",
        "Owned": "FALSE",
        "Last Scrape": "2025-03-20 18:12"
    },
    {
        "Release Date": "2020-11",
        "Set": "Commander Legends (Collectors)",
        "Link": "https://www.tcgplayer.com/product/221322/magic-commander-legends-commander-legends-collector-booster-pack?Language=English&page=1",
        "Current Price": "$41.99",
        "Bought At": "",
        "Owned": "FALSE",
        "Last Scrape": "2025-03-20 18:12"
    },
    {
        "Release Date": "2021-02",
        "Set": "Kaldheim (Set)",
        "Link": "https://www.tcgplayer.com/product/228252/magic-kaldheim-kaldheim-set-booster-pack?Language=English&page=1",
        "Current Price": "$4.99",
        "Bought At": "",
        "Owned": "FALSE",
        "Last Scrape": "2025-03-20 18:12"
    },
    {
        "Release Date": "2021-02",
        "Set": "Kaldheim (Draft)",
        "Link": "https://www.tcgplayer.com/product/228246/magic-kaldheim-kaldheim-draft-booster-pack?Language=English&page=1",
        "Current Price": "$4.34",
        "Bought At": "",
        "Owned": "FALSE",
        "Last Scrape": "2025-03-20 18:12"
    },
    {
        "Release Date": "2021-02",
        "Set": "Kaldheim (Theme)",
        "Link": "https://www.tcgplayer.com/product/229244/magic-kaldheim-kaldheim-theme-booster-set-of-6?Language=English&page=1",
        "Current Price": "$59.14",
        "Bought At": "",
        "Owned": "FALSE",
        "Last Scrape": "2025-03-20 18:12"
    },
    {
        "Release Date": "2021-02",
        "Set": "Kaldheim (Collectors)",
        "Link": "https://www.tcgplayer.com/product/228250/magic-kaldheim-kaldheim-collector-booster-pack?Language=English&page=1",
        "Current Price": "$24.24",
        "Bought At": "",
        "Owned": "FALSE",
        "Last Scrape": "2025-03-20 18:12"
    },
    {
        "Release Date": "2021-03",
        "Set": "Time Spiral Remastered",
        "Link": "https://www.tcgplayer.com/product/230383/magic-time-spiral-remastered-time-spiral-remastered-draft-booster-pack?Language=English&page=1",
        "Current Price": "$9.60",
        "Bought At": "",
        "Owned": "FALSE",
        "Last Scrape": "2025-03-20 18:12"
    },
    {
        "Release Date": "2021-04",
        "Set": "Strixhaven: School of Mages (Set)",
        "Link": "https://www.tcgplayer.com/product/233228/magic-strixhaven-school-of-mages-strixhaven-school-of-mages-set-booster-pack?Language=English&page=1",
        "Current Price": "$4.99",
        "Bought At": "",
        "Owned": "FALSE",
        "Last Scrape": "2025-03-20 18:12"
    },
    {
        "Release Date": "2021-04",
        "Set": "Strixhaven: School of Mages (Draft)",
        "Link": "https://www.tcgplayer.com/product/233248/magic-strixhaven-school-of-mages-strixhaven-school-of-mages-draft-booster-pack?Language=English&page=1",
        "Current Price": "$4.34",
        "Bought At": "",
        "Owned": "FALSE",
        "Last Scrape": "2025-03-20 18:12"
    },
    {
        "Release Date": "2021-04",
        "Set": "Strixhaven: School of Mages (Theme)",
        "Link": "https://www.tcgplayer.com/product/233261/magic-strixhaven-school-of-mages-strixhaven-school-of-mages-theme-booster-set-of-5?Language=English&page=1",
        "Current Price": "$37.49",
        "Bought At": "",
        "Owned": "FALSE",
        "Last Scrape": "2025-03-20 18:12"
    },
    {
        "Release Date": "2021-04",
        "Set": "Strixhaven: School of Mages (Collectors)",
        "Link": "https://www.tcgplayer.com/product/233230/magic-strixhaven-school-of-mages-strixhaven-school-of-mages-collector-booster-pack?Language=English&page=1",
        "Current Price": "$31.99",
        "Bought At": "",
        "Owned": "FALSE",
        "Last Scrape": "2025-03-20 18:12"
    },
    {
        "Release Date": "2021-06",
        "Set": "Modern Horizons II (Set)",
        "Link": "https://www.tcgplayer.com/product/236351/magic-modern-horizons-2-modern-horizons-2-set-booster-pack?Language=English&page=1",
        "Current Price": "$9.79",
        "Bought At": "",
        "Owned": "FALSE",
        "Last Scrape": "2025-03-20 18:12"
    },
    {
        "Release Date": "2021-06",
        "Set": "Modern Horizons II (Draft)",
        "Link": "https://www.tcgplayer.com/product/236356/magic-modern-horizons-2-modern-horizons-2-draft-booster-pack?Language=English&page=1",
        "Current Price": "$6.74",
        "Bought At": "",
        "Owned": "FALSE",
        "Last Scrape": "2025-03-20 18:12"
    },
    {
        "Release Date": "2021-06",
        "Set": "Modern Horizons II (Collectors)",
        "Link": "https://www.tcgplayer.com/product/236349/magic-modern-horizons-2-modern-horizons-2-collector-booster-pack?Language=English&page=1",
        "Current Price": "$34.01",
        "Bought At": "",
        "Owned": "FALSE",
        "Last Scrape": "2025-03-20 18:12"
    },
    {
        "Release Date": "2021-07",
        "Set": "Adventures in the Forgotten Realms (Set)",
        "Link": "https://www.tcgplayer.com/product/238741/magic-adventures-in-the-forgotten-realms-adventures-in-the-forgotten-realms-set-booster-pack?Language=English&page=1",
        "Current Price": "$5.74",
        "Bought At": "",
        "Owned": "FALSE",
        "Last Scrape": "2025-03-20 18:12"
    },
    {
        "Release Date": "2021-07",
        "Set": "Adventures in the Forgotten Realms (Draft)",
        "Link": "https://www.tcgplayer.com/product/238731/magic-adventures-in-the-forgotten-realms-adventures-in-the-forgotten-realms-draft-booster-pack?Language=English&page=1",
        "Current Price": "$5.25",
        "Bought At": "",
        "Owned": "FALSE",
        "Last Scrape": "2025-03-20 18:12"
    },
    {
        "Release Date": "2021-07",
        "Set": "Adventures in the Forgotten Realms (Theme)",
        "Link": "https://www.tcgplayer.com/product/238820/magic-adventures-in-the-forgotten-realms-adventures-in-the-forgotten-realms-theme-booster-set-of-6?Language=English&page=1",
        "Current Price": "$49.94",
        "Bought At": "",
        "Owned": "FALSE",
        "Last Scrape": "2025-03-20 18:12"
    },
    {
        "Release Date": "2021-07",
        "Set": "Adventures in the Forgotten Realms (Collectors)",
        "Link": "https://www.tcgplayer.com/product/238746/magic-adventures-in-the-forgotten-realms-adventures-in-the-forgotten-realms-collector-booster-pack?Language=English&page=1",
        "Current Price": "$21.75",
        "Bought At": "",
        "Owned": "FALSE",
        "Last Scrape": "2025-03-20 18:12"
    },
    {
        "Release Date": "2021-09",
        "Set": "Innistrad: Midnight Hunt (Set)",
        "Link": "https://www.tcgplayer.com/product/244387/magic-innistrad-midnight-hunt-innistrad-midnight-hunt-set-booster-pack?Language=English&page=1",
        "Current Price": "$4.97",
        "Bought At": "",
        "Owned": "FALSE",
        "Last Scrape": "2025-03-20 18:12"
    },
    {
        "Release Date": "2021-09",
        "Set": "Innistrad: Midnight Hunt (Draft)",
        "Link": "https://www.tcgplayer.com/product/244378/magic-innistrad-midnight-hunt-innistrad-midnight-hunt-draft-booster-pack?Language=English&page=1",
        "Current Price": "$3.98",
        "Bought At": "",
        "Owned": "FALSE",
        "Last Scrape": "2025-03-20 18:12"
    },
    {
        "Release Date": "2021-09",
        "Set": "Innistrad: Midnight Hunt (Theme)",
        "Link": "https://www.tcgplayer.com/product/247368/magic-innistrad-midnight-hunt-innistrad-midnight-hunt-theme-booster-set-of-6?Language=English&page=1",
        "Current Price": "$44.99",
        "Bought At": "",
        "Owned": "FALSE",
        "Last Scrape": "2025-03-20 18:12"
    },
    {
        "Release Date": "2021-09",
        "Set": "Innistrad: Midnight Hunt (Collectors)",
        "Link": "https://www.tcgplayer.com/product/244383/magic-innistrad-midnight-hunt-innistrad-midnight-hunt-collector-booster-pack?Language=English&page=1",
        "Current Price": "$16.00",
        "Bought At": "",
        "Owned": "FALSE",
        "Last Scrape": "2025-03-20 18:12"
    },
    {
        "Release Date": "2021-11",
        "Set": "Innistrad: Crimson Vow (Set)",
        "Link": "https://www.tcgplayer.com/product/246472/magic-innistrad-crimson-vow-innistrad-crimson-vow-set-booster-pack?Language=English&page=1",
        "Current Price": "$5.78",
        "Bought At": "",
        "Owned": "FALSE",
        "Last Scrape": "2025-03-20 18:12"
    },
    {
        "Release Date": "2021-11",
        "Set": "Innistrad: Crimson Vow (Draft)",
        "Link": "https://www.tcgplayer.com/product/246469/magic-innistrad-crimson-vow-innistrad-crimson-vow-draft-booster-pack?Language=English&page=1",
        "Current Price": "$3.99",
        "Bought At": "",
        "Owned": "FALSE",
        "Last Scrape": "2025-03-20 18:12"
    },
    {
        "Release Date": "2021-11",
        "Set": "Innistrad: Crimson Vow (Theme)",
        "Link": "https://www.tcgplayer.com/product/253822/magic-innistrad-crimson-vow-innistrad-crimson-vow-theme-booster-set-of-6?Language=English&page=1",
        "Current Price": "$49.95",
        "Bought At": "",
        "Owned": "FALSE",
        "Last Scrape": "2025-03-20 18:12"
    },
    {
        "Release Date": "2021-11",
        "Set": "Innistrad: Crimson Vow (Collectors)",
        "Link": "https://www.tcgplayer.com/product/246459/magic-innistrad-crimson-vow-innistrad-crimson-vow-collector-booster-pack?Language=English&page=1",
        "Current Price": "$17.40",
        "Bought At": "",
        "Owned": "FALSE",
        "Last Scrape": "2025-03-20 18:12"
    },
    {
        "Release Date": "2022-01",
        "Set": "Innistrad: Double Feature",
        "Link": "https://www.tcgplayer.com/product/255912/Magic-Innistrad%20Double%20Feature-Innistrad%20Double%20Feature%20Draft%20Booster%20Pack?xid=ae8d7b623-fdbf-4d3b-b20e-ac096eee1190&Language=English",
        "Current Price": "$9.90",
        "Bought At": "",
        "Owned": "FALSE",
        "Last Scrape": "2025-03-20 18:12"
    },
    {
        "Release Date": "2022-02",
        "Set": "Kamigawa: Neon Dynasty (Set)",
        "Link": "https://www.tcgplayer.com/product/257561/magic-kamigawa-neon-dynasty-kamigawa-neon-dynasty-set-booster-pack?Language=English&page=1",
        "Current Price": "$6.95",
        "Bought At": "",
        "Owned": "FALSE",
        "Last Scrape": "2025-03-20 18:12"
    },
    {
        "Release Date": "2022-02",
        "Set": "Kamigawa: Neon Dynasty (Draft)",
        "Link": "https://www.tcgplayer.com/product/257556/magic-kamigawa-neon-dynasty-kamigawa-neon-dynasty-draft-booster-pack?Language=English&page=1",
        "Current Price": "$4.93",
        "Bought At": "",
        "Owned": "FALSE",
        "Last Scrape": "2025-03-20 18:12"
    },
    {
        "Release Date": "2022-02",
        "Set": "Kamigawa: Neon Dynasty (Theme)",
        "Link": "https://www.tcgplayer.com/product/257575/magic-kamigawa-neon-dynasty-kamigawa-neon-dynasty-theme-booster-set-of-6?Language=English&page=1",
        "Current Price": "$46.00",
        "Bought At": "",
        "Owned": "FALSE",
        "Last Scrape": "2025-03-20 18:12"
    },
    {
        "Release Date": "2022-02",
        "Set": "Kamigawa: Neon Dynasty (Collectors)",
        "Link": "https://www.tcgplayer.com/product/257562/magic-kamigawa-neon-dynasty-kamigawa-neon-dynasty-collector-booster-pack?Language=English&page=1",
        "Current Price": "$25.99",
        "Bought At": "",
        "Owned": "FALSE",
        "Last Scrape": "2025-03-20 18:12"
    },
    {
        "Release Date": "2022-05",
        "Set": "Streets of New Capenna (Set)",
        "Link": "https://www.tcgplayer.com/product/264765/magic-streets-of-new-capenna-streets-of-new-capenna-set-booster-pack?Language=English&page=1",
        "Current Price": "$5.01",
        "Bought At": "",
        "Owned": "FALSE",
        "Last Scrape": "2025-03-20 18:12"
    },
    {
        "Release Date": "2022-05",
        "Set": "Streets of New Capenna (Draft)",
        "Link": "https://www.tcgplayer.com/product/264759/magic-streets-of-new-capenna-streets-of-new-capenna-draft-booster-pack?Language=English&page=1",
        "Current Price": "$3.67",
        "Bought At": "",
        "Owned": "FALSE",
        "Last Scrape": "2025-03-20 18:12"
    },
    {
        "Release Date": "2022-05",
        "Set": "Streets of New Capenna (Theme)",
        "Link": "https://www.tcgplayer.com/product/265364/magic-streets-of-new-capenna-streets-of-new-capenna-theme-booster-set-of-5?Language=English&page=1",
        "Current Price": "$39.99",
        "Bought At": "",
        "Owned": "FALSE",
        "Last Scrape": "2025-03-20 18:12"
    },
    {
        "Release Date": "2022-05",
        "Set": "Streets of New Capenna (Collectors)",
        "Link": "https://www.tcgplayer.com/product/264766/magic-streets-of-new-capenna-streets-of-new-capenna-collector-booster-pack?Language=English&page=1",
        "Current Price": "$17.30",
        "Bought At": "",
        "Owned": "FALSE",
        "Last Scrape": "2025-03-20 18:12"
    },
    {
        "Release Date": "2022-06",
        "Set": "Commander Legends: Battle for Baldur's Gate (Set)",
        "Link": "https://www.tcgplayer.com/product/267021/magic-commander-legends-battle-for-baldurs-gate-commander-legends-battle-for-baldurs-gate-set-booster-pack?Language=English&page=1",
        "Current Price": "$8.21",
        "Bought At": "",
        "Owned": "FALSE",
        "Last Scrape": "2025-03-20 18:12"
    },
    {
        "Release Date": "2022-06",
        "Set": "Commander Legends: Battle for Baldur's Gate (Draft)",
        "Link": "https://www.tcgplayer.com/product/267020/magic-commander-legends-battle-for-baldurs-gate-commander-legends-battle-for-baldurs-gate-draft-booster-pack?Language=English&page=1",
        "Current Price": "$7.67",
        "Bought At": "",
        "Owned": "FALSE",
        "Last Scrape": "2025-03-20 18:12"
    },
    {
        "Release Date": "2022-06",
        "Set": "Commander Legends: Battle for Baldur's Gate (Collectors)",
        "Link": "https://www.tcgplayer.com/product/267024/magic-commander-legends-battle-for-baldurs-gate-commander-legends-battle-for-baldurs-gate-collector-booster-pack?Language=English&page=1",
        "Current Price": "$28.50",
        "Bought At": "",
        "Owned": "FALSE",
        "Last Scrape": "2025-03-20 18:12"
    },
    {
        "Release Date": "2022-07",
        "Set": "Double Masters 2022 (Draft)",
        "Link": "https://www.tcgplayer.com/product/271507/magic-double-masters-2022-double-masters-2022-draft-booster-pack?Language=English&page=1",
        "Current Price": "$14.50",
        "Bought At": "",
        "Owned": "FALSE",
        "Last Scrape": "2025-03-20 18:12"
    },
    {
        "Release Date": "2022-07",
        "Set": "Double Masters 2022 (Collectors)",
        "Link": "https://www.tcgplayer.com/product/271508/magic-double-masters-2022-double-masters-2022-collector-booster-pack?Language=English&page=1",
        "Current Price": "$71.50",
        "Bought At": "",
        "Owned": "FALSE",
        "Last Scrape": "2025-03-20 18:12"
    },
    {
        "Release Date": "2022-09",
        "Set": "Dominaria United (Set)",
        "Link": "https://www.tcgplayer.com/product/275405/magic-dominaria-united-dominaria-united-set-booster-pack?Language=English&page=1",
        "Current Price": "$5.63",
        "Bought At": "",
        "Owned": "FALSE",
        "Last Scrape": "2025-03-20 18:12"
    },
    {
        "Release Date": "2022-09",
        "Set": "Dominaria United (Draft)",
        "Link": "https://www.tcgplayer.com/product/275432/magic-dominaria-united-dominaria-united-draft-booster-pack?Language=English&page=1",
        "Current Price": "$3.43",
        "Bought At": "",
        "Owned": "FALSE",
        "Last Scrape": "2025-03-20 18:12"
    },
    {
        "Release Date": "2022-09",
        "Set": "Dominaria United (Collectors)",
        "Link": "https://www.tcgplayer.com/product/275407/magic-dominaria-united-dominaria-united-collector-booster-pack?Language=English&page=1",
        "Current Price": "$18.00",
        "Bought At": "",
        "Owned": "FALSE",
        "Last Scrape": "2025-03-20 18:12"
    },
    {
        "Release Date": "2022-10",
        "Set": "Unfinity (Draft)",
        "Link": "https://www.tcgplayer.com/product/275408/magic-unfinity-unfinity-draft-booster-pack?Language=English&page=1",
        "Current Price": "$4.14",
        "Bought At": "",
        "Owned": "FALSE",
        "Last Scrape": "2025-03-20 18:12"
    },
    {
        "Release Date": "2022-10",
        "Set": "Unfinity (Collectors)",
        "Link": "https://www.tcgplayer.com/product/275409/magic-unfinity-unfinity-collector-booster-pack?Language=English&page=1",
        "Current Price": "$20.60",
        "Bought At": "",
        "Owned": "FALSE",
        "Last Scrape": "2025-03-20 18:12"
    },
    {
        "Release Date": "2022-11",
        "Set": "The Brothers' War (Set)",
        "Link": "https://www.tcgplayer.com/product/282231/magic-the-brothers-war-the-brothers-war-set-booster-pack?Language=English&page=1",
        "Current Price": "$6.90",
        "Bought At": "",
        "Owned": "FALSE",
        "Last Scrape": "2025-03-20 18:12"
    },
    {
        "Release Date": "2022-11",
        "Set": "The Brothers' War (Draft)",
        "Link": "https://www.tcgplayer.com/product/282227/magic-the-brothers-war-the-brothers-war-draft-booster-pack?Language=English&page=1",
        "Current Price": "$4.40",
        "Bought At": "",
        "Owned": "FALSE",
        "Last Scrape": "2025-03-20 18:12"
    },
    {
        "Release Date": "2022-11",
        "Set": "The Brothers' War (Collectors)",
        "Link": "https://www.tcgplayer.com/product/282223/magic-the-brothers-war-the-brothers-war-collector-booster-pack?Language=English&page=1",
        "Current Price": "$26.00",
        "Bought At": "",
        "Owned": "FALSE",
        "Last Scrape": "2025-03-20 18:12"
    },
    {
        "Release Date": "2022-12",
        "Set": "Jumpstart 2022",
        "Link": "https://www.tcgplayer.com/product/287814/magic-jumpstart-2022-jumpstart-2022-booster-pack?Language=English&page=1",
        "Current Price": "$6.49",
        "Bought At": "",
        "Owned": "FALSE",
        "Last Scrape": "2025-03-20 18:12"
    },
    {
        "Release Date": "2023-01",
        "Set": "Dominaria Remastered (Draft)",
        "Link": "https://www.tcgplayer.com/product/449571/magic-dominaria-remastered-dominaria-remastered-draft-booster-pack?Language=English&page=1",
        "Current Price": "$4.48",
        "Bought At": "",
        "Owned": "FALSE",
        "Last Scrape": "2025-03-20 18:12"
    },
    {
        "Release Date": "2023-01",
        "Set": "Dominaria Remastered (Collectors)",
        "Link": "https://www.tcgplayer.com/product/449570/magic-dominaria-remastered-dominaria-remastered-collector-booster-pack?Language=English&page=1",
        "Current Price": "$23.50",
        "Bought At": "",
        "Owned": "FALSE",
        "Last Scrape": "2025-03-20 18:12"
    },
    {
        "Release Date": "2023-02",
        "Set": "Phyrexia: All Will Be One (Set)",
        "Link": "https://www.tcgplayer.com/product/451871/magic-phyrexia-all-will-be-one-phyrexia-all-will-be-one-set-booster-pack?Language=English&page=1",
        "Current Price": "$5.38",
        "Bought At": "",
        "Owned": "FALSE",
        "Last Scrape": "2025-03-20 18:12"
    },
    {
        "Release Date": "2023-02",
        "Set": "Phyrexia: All Will Be One (Draft)",
        "Link": "https://www.tcgplayer.com/product/451868/magic-phyrexia-all-will-be-one-phyrexia-all-will-be-one-draft-booster-pack?Language=English&page=1",
        "Current Price": "$4.94",
        "Bought At": "",
        "Owned": "FALSE",
        "Last Scrape": "2025-03-20 18:12"
    },
    {
        "Release Date": "2023-02",
        "Set": "Phyrexia: All Will Be One (Collectors)",
        "Link": "https://www.tcgplayer.com/product/451879/magic-phyrexia-all-will-be-one-phyrexia-all-will-be-one-collector-booster-pack?Language=English&page=1",
        "Current Price": "$42.99",
        "Bought At": "",
        "Owned": "FALSE",
        "Last Scrape": "2025-03-20 18:12"
    },
    {
        "Release Date": "2023-04",
        "Set": "March of the Machine (Set)",
        "Link": "https://www.tcgplayer.com/product/475578/magic-march-of-the-machine-march-of-the-machine-set-booster-pack?Language=English&page=1",
        "Current Price": "$4.69",
        "Bought At": "",
        "Owned": "FALSE",
        "Last Scrape": "2025-03-20 18:12"
    },
    {
        "Release Date": "2023-04",
        "Set": "March of the Machine (Draft)",
        "Link": "https://www.tcgplayer.com/product/475577/magic-march-of-the-machine-march-of-the-machine-draft-booster-pack?Language=English&page=1",
        "Current Price": "$4.20",
        "Bought At": "",
        "Owned": "FALSE",
        "Last Scrape": "2025-03-20 18:12"
    },
    {
        "Release Date": "2023-04",
        "Set": "March of the Machine (Collectors)",
        "Link": "https://www.tcgplayer.com/product/475583/magic-march-of-the-machine-march-of-the-machine-collector-booster-pack?Language=English&page=1",
        "Current Price": "$29.95",
        "Bought At": "",
        "Owned": "FALSE",
        "Last Scrape": "2025-03-20 18:12"
    },
    {
        "Release Date": "2023-05",
        "Set": "March of the Machine: The Aftermath",
        "Link": "https://www.tcgplayer.com/product/489274/magic-march-of-the-machine-the-aftermath-march-of-the-machine-the-aftermath-epilogue-booster-pack?Language=English&page=1",
        "Current Price": "$4.55",
        "Bought At": "",
        "Owned": "FALSE",
        "Last Scrape": "2025-03-20 18:12"
    },
    {
        "Release Date": "2023-05",
        "Set": "March of the Machine: The Aftermath (Collectors)",
        "Link": "https://www.tcgplayer.com/product/489204/magic-march-of-the-machine-the-aftermath-march-of-the-machine-the-aftermath-collector-booster-pack?Language=English&page=1",
        "Current Price": "$17.45",
        "Bought At": "",
        "Owned": "FALSE",
        "Last Scrape": "2025-03-20 18:12"
    },
    {
        "Release Date": "2023-06",
        "Set": "The Lord of the Rings: Tales of Middle-Earth (Set)",
        "Link": "https://www.tcgplayer.com/product/484908/magic-universes-beyond-the-lord-of-the-rings-tales-of-middle-earth-universes-beyond-the-lord-of-the-rings-tales-of-middle-earth-set-booster-pack?Language=English&page=1",
        "Current Price": "$8.92",
        "Bought At": "",
        "Owned": "FALSE",
        "Last Scrape": "2025-03-20 18:12"
    },
    {
        "Release Date": "2023-06",
        "Set": "The Lord of the Rings: Tales of Middle-Earth (Draft)",
        "Link": "https://www.tcgplayer.com/product/484905/magic-universes-beyond-the-lord-of-the-rings-tales-of-middle-earth-universes-beyond-the-lord-of-the-rings-tales-of-middle-earth-draft-booster-pack?Language=English&page=1",
        "Current Price": "$6.89",
        "Bought At": "",
        "Owned": "FALSE",
        "Last Scrape": "2025-03-20 18:12"
    },
    {
        "Release Date": "2023-06",
        "Set": "The Lord of the Rings: Tales of Middle-Earth (Collectors)",
        "Link": "https://www.tcgplayer.com/product/484911/magic-universes-beyond-the-lord-of-the-rings-tales-of-middle-earth-universes-beyond-the-lord-of-the-rings-tales-of-middle-earth-collector-booster-pack?Language=English&page=1",
        "Current Price": "$72.89",
        "Bought At": "",
        "Owned": "FALSE",
        "Last Scrape": "2025-03-20 18:12"
    },
    {
        "Release Date": "2023-06",
        "Set": "The Lord of the Rings: Tales of Middle-Earth (Collectors SE)",
        "Link": "https://www.tcgplayer.com/product/515905/magic-universes-beyond-the-lord-of-the-rings-tales-of-middle-earth-the-lord-of-the-rings-tales-of-middle-earth-special-edition-collector-booster-pack?Language=English&page=1",
        "Current Price": "$145.99",
        "Bought At": "",
        "Owned": "FALSE",
        "Last Scrape": "2025-03-20 18:12"
    },
    {
        "Release Date": "2023-08",
        "Set": "Commander Masters (Set)",
        "Link": "https://www.tcgplayer.com/product/484926/magic-commander-masters-commander-masters-set-booster-pack?Language=English&page=1",
        "Current Price": "$17.48",
        "Bought At": "",
        "Owned": "FALSE",
        "Last Scrape": "2025-03-20 18:12"
    },
    {
        "Release Date": "2023-08",
        "Set": "Commander Masters (Draft)",
        "Link": "https://www.tcgplayer.com/product/484923/magic-commander-masters-commander-masters-draft-booster-pack?Language=English&page=1",
        "Current Price": "$17.95",
        "Bought At": "",
        "Owned": "FALSE",
        "Last Scrape": "2025-03-20 18:12"
    },
    {
        "Release Date": "2023-08",
        "Set": "Commander Masters (Collectors)",
        "Link": "https://www.tcgplayer.com/product/484928/magic-commander-masters-commander-masters-collector-booster-pack?Language=English&page=1",
        "Current Price": "$61.84",
        "Bought At": "",
        "Owned": "FALSE",
        "Last Scrape": "2025-03-20 18:12"
    },
    {
        "Release Date": "2023-09",
        "Set": "Wilds of Eldraine (Set)",
        "Link": "https://www.tcgplayer.com/product/496037/magic-wilds-of-eldraine-wilds-of-eldraine-set-booster-pack?Language=English&page=1",
        "Current Price": "$6.94",
        "Bought At": "",
        "Owned": "FALSE",
        "Last Scrape": "2025-03-20 18:12"
    },
    {
        "Release Date": "2023-09",
        "Set": "Wilds of Eldraine (Draft)",
        "Link": "https://www.tcgplayer.com/product/496034/magic-wilds-of-eldraine-wilds-of-eldraine-draft-booster-pack?Language=English&page=1",
        "Current Price": "$4.63",
        "Bought At": "",
        "Owned": "FALSE",
        "Last Scrape": "2025-03-20 18:12"
    },
    {
        "Release Date": "2023-09",
        "Set": "Wilds of Eldraine (Collectors)",
        "Link": "https://www.tcgplayer.com/product/496040/magic-wilds-of-eldraine-wilds-of-eldraine-collector-booster-pack?Language=English&page=1",
        "Current Price": "$44.95",
        "Bought At": "",
        "Owned": "FALSE",
        "Last Scrape": "2025-03-20 18:12"
    },
    {
        "Release Date": "2023-11",
        "Set": "The Lost Caverns of Ixalan (Set)",
        "Link": "https://www.tcgplayer.com/product/516621/magic-the-lost-caverns-of-ixalan-the-lost-caverns-of-ixalan-set-booster-pack?Language=English&page=1",
        "Current Price": "$5.23",
        "Bought At": "",
        "Owned": "FALSE",
        "Last Scrape": "2025-03-20 18:12"
    },
    {
        "Release Date": "2023-11",
        "Set": "The Lost Caverns of Ixalan (Draft)",
        "Link": "https://www.tcgplayer.com/product/516618/magic-the-lost-caverns-of-ixalan-the-lost-caverns-of-ixalan-draft-booster-pack?Language=English&page=1",
        "Current Price": "$4.49",
        "Bought At": "",
        "Owned": "FALSE",
        "Last Scrape": "2025-03-20 18:12"
    },
    {
        "Release Date": "2023-11",
        "Set": "The Lost Caverns of Ixalan (Collectors)",
        "Link": "https://www.tcgplayer.com/product/516613/magic-the-lost-caverns-of-ixalan-the-lost-caverns-of-ixalan-collector-booster-pack?Language=English&page=1",
        "Current Price": "$32.29",
        "Bought At": "",
        "Owned": "FALSE",
        "Last Scrape": "2025-03-20 18:12"
    },
    {
        "Release Date": "2024-01",
        "Set": "Ravnica Remastered (Draft)",
        "Link": "https://www.tcgplayer.com/product/517704/magic-ravnica-remastered-ravnica-remastered-draft-booster-pack?Language=English&page=1",
        "Current Price": "$6.24",
        "Bought At": "",
        "Owned": "FALSE",
        "Last Scrape": "2025-03-20 18:12"
    },
    {
        "Release Date": "2024-01",
        "Set": "Ravnica Remastered (Collectors)",
        "Link": "https://www.tcgplayer.com/product/517707/magic-ravnica-remastered-ravnica-remastered-collector-booster-pack?Language=English&page=1",
        "Current Price": "$53.89",
        "Bought At": "",
        "Owned": "FALSE",
        "Last Scrape": "2025-03-20 18:12"
    },
    {
        "Release Date": "2024-02",
        "Set": "Murders at Karlov Manor (Play)",
        "Link": "https://www.tcgplayer.com/product/529962/magic-murders-at-karlov-manor-murders-at-karlov-manor-play-booster-pack?Language=English&page=1",
        "Current Price": "$3.62",
        "Bought At": "",
        "Owned": "FALSE",
        "Last Scrape": "2025-03-20 18:12"
    },
    {
        "Release Date": "2024-02",
        "Set": "Murders at Karlov Manor (Collectors)",
        "Link": "https://www.tcgplayer.com/product/529967/magic-murders-at-karlov-manor-murders-at-karlov-manor-collector-booster-pack?Language=English&page=1",
        "Current Price": "$19.01",
        "Bought At": "",
        "Owned": "FALSE",
        "Last Scrape": "2025-03-20 18:12"
    },
    {
        "Release Date": "2024-03",
        "Set": "Fallout (Collectors)",
        "Link": "https://www.tcgplayer.com/product/523180/magic-universes-beyond-fallout-universes-beyond-fallout-collector-booster-pack?Language=English&page=1",
        "Current Price": "$106.89",
        "Bought At": "",
        "Owned": "FALSE",
        "Last Scrape": "2025-03-20 18:12"
    },
    {
        "Release Date": "2024-04",
        "Set": "Outlaws of Thunder Junction (Play)",
        "Link": "https://www.tcgplayer.com/product/541083/magic-outlaws-of-thunder-junction-outlaws-of-thunder-junction-play-booster-pack?Language=English&page=1",
        "Current Price": "$4.75",
        "Bought At": "",
        "Owned": "FALSE",
        "Last Scrape": "2025-03-20 18:12"
    },
    {
        "Release Date": "2024-04",
        "Set": "Outlaws of Thunder Junction (Collectors)",
        "Link": "https://www.tcgplayer.com/product/541086/magic-outlaws-of-thunder-junction-outlaws-of-thunder-junction-collector-booster-pack?Language=English&page=1",
        "Current Price": "$18.97",
        "Bought At": "",
        "Owned": "FALSE",
        "Last Scrape": "2025-03-20 18:12"
    },
    {
        "Release Date": "2024-06",
        "Set": "Modern Horizons III (Play)",
        "Link": "https://www.tcgplayer.com/product/541163/magic-modern-horizons-3-modern-horizons-3-play-booster-pack?Language=English&page=1",
        "Current Price": "$8.84",
        "Bought At": "",
        "Owned": "FALSE",
        "Last Scrape": "2025-03-20 18:12"
    },
    {
        "Release Date": "2024-06",
        "Set": "Modern Horizons III (Collectors)",
        "Link": "https://www.tcgplayer.com/product/541173/magic-modern-horizons-3-modern-horizons-3-collector-booster-pack?Language=English&page=1",
        "Current Price": "$39.69",
        "Bought At": "",
        "Owned": "FALSE",
        "Last Scrape": "2025-03-20 18:12"
    },
    {
        "Release Date": "2024-07",
        "Set": "Assassin's Creed (Beyond)",
        "Link": "https://www.tcgplayer.com/product/541218/magic-universes-beyond-assassins-creed-universes-beyond-assassins-creed-beyond-booster-pack?Language=English&page=1",
        "Current Price": "$6.66",
        "Bought At": "",
        "Owned": "FALSE",
        "Last Scrape": "2025-03-20 18:12"
    },
    {
        "Release Date": "2024-07",
        "Set": "Assassin's Creed (Collectors)",
        "Link": "https://www.tcgplayer.com/product/541224/magic-universes-beyond-assassins-creed-universes-beyond-assassins-creed-collector-booster-pack?Language=English&page=1",
        "Current Price": "$21.97",
        "Bought At": "",
        "Owned": "FALSE",
        "Last Scrape": "2025-03-20 18:12"
    },
    {
        "Release Date": "2024-08",
        "Set": "Bloomburrow (Play)",
        "Link": "https://www.tcgplayer.com/product/541234/magic-bloomburrow-bloomburrow-play-booster-pack?Language=English&page=1",
        "Current Price": "$5.89",
        "Bought At": "",
        "Owned": "FALSE",
        "Last Scrape": "2025-03-20 18:12"
    },
    {
        "Release Date": "2024-08",
        "Set": "Bloomburrow (Collectors)",
        "Link": "https://www.tcgplayer.com/product/541237/magic-bloomburrow-bloomburrow-collector-booster-pack?Language=English&page=1",
        "Current Price": "$43.94",
        "Bought At": "",
        "Owned": "FALSE",
        "Last Scrape": "2025-03-20 18:12"
    },
    {
        "Release Date": "2024-08",
        "Set": "Mystery Booster 2",
        "Link": "https://www.tcgplayer.com/product/563749/magic-mystery-booster-2-mystery-booster-2-booster-pack?Language=English&page=1",
        "Current Price": "$13.97",
        "Bought At": "",
        "Owned": "FALSE",
        "Last Scrape": "2025-03-20 18:12"
    },
    {
        "Release Date": "2024-09",
        "Set": "Duskmourn: House of Horror (Play)",
        "Link": "https://www.tcgplayer.com/product/557240/magic-duskmourn-house-of-horror-duskmourn-house-of-horror-play-booster-pack?Language=English&page=1",
        "Current Price": "$4.93",
        "Bought At": "",
        "Owned": "FALSE",
        "Last Scrape": "2025-03-20 18:12"
    },
    {
        "Release Date": "2024-09",
        "Set": "Duskmourn: House of Horror (Collectors)",
        "Link": "https://www.tcgplayer.com/product/557243/magic-duskmourn-house-of-horror-duskmourn-house-of-horror-collector-booster-pack?Language=English&page=1",
        "Current Price": "$26.80",
        "Bought At": "",
        "Owned": "FALSE",
        "Last Scrape": "2025-03-20 18:12"
    },
    {
        "Release Date": "2024-11",
        "Set": "Magic: The Gathering Foundations (Play)",
        "Link": "https://www.tcgplayer.com/product/562116/magic-foundations-magic-the-gathering-foundations-play-booster-pack?Language=English&page=1",
        "Current Price": "$4.94",
        "Bought At": "",
        "Owned": "FALSE",
        "Last Scrape": "2025-03-20 18:12"
    },
    {
        "Release Date": "2024-11",
        "Set": "Magic: The Gathering Foundations (Collectors)",
        "Link": "https://www.tcgplayer.com/product/562121/magic-foundations-magic-the-gathering-foundations-collector-booster-pack?Language=English&page=1",
        "Current Price": "$48.99",
        "Bought At": "",
        "Owned": "FALSE",
        "Last Scrape": "2025-03-20 18:12"
    },
    {
        "Release Date": "2025-01",
        "Set": "Innistrad Remastered (Play)",
        "Link": "https://www.tcgplayer.com/product/594669/magic-innistrad-remastered-innistrad-remastered-play-booster-pack?Language=English&page=1",
        "Current Price": "$5.58",
        "Bought At": "",
        "Owned": "FALSE",
        "Last Scrape": "2025-03-20 18:12"
    },
    {
        "Release Date": "2025-01",
        "Set": "Innistrad Remastered (Collectors)",
        "Link": "https://www.tcgplayer.com/product/594678/magic-innistrad-remastered-innistrad-remastered-collector-booster-pack?Language=English&page=1",
        "Current Price": "$25.60",
        "Bought At": "",
        "Owned": "FALSE",
        "Last Scrape": "2025-03-20 18:12"
    },
    {
        "Release Date": "2025-02",
        "Set": "Aetherdrift (Play)",
        "Link": "https://www.tcgplayer.com/product/604249/magic-aetherdrift-aetherdrift-play-booster-pack?Language=English&page=1",
        "Current Price": "$3.13",
        "Bought At": "",
        "Owned": "FALSE",
        "Last Scrape": "2025-03-20 18:12"
    },
    {
        "Release Date": "2025-02",
        "Set": "Aetherdrift (Collectors)",
        "Link": "https://www.tcgplayer.com/product/604252/magic-aetherdrift-aetherdrift-collector-booster-pack?Language=English&page=1",
        "Current Price": "$17.20",
        "Bought At": "",
        "Owned": "FALSE",
        "Last Scrape": "2025-03-20 18:12"
    },
    {
        "Release Date": "2025-04",
        "Set": "Tarkir: Dragonstorm (Play)",
        "Link": "https://www.tcgplayer.com/product/619644/magic-tarkir-dragonstorm-tarkir-dragonstorm-play-booster?Language=English&page=1",
        "Current Price": "$8.97",
        "Bought At": "",
        "Owned": "FALSE",
        "Last Scrape": "2025-03-20 18:12"
    },
    {
        "Release Date": "2025-04",
        "Set": "Tarkir: Dragonstorm (Collectors)",
        "Link": "https://www.tcgplayer.com/product/619648/magic-tarkir-dragonstorm-tarkir-dragonstorm-collector-booster?Language=English&page=1",
        "Current Price": "$27.90",
        "Bought At": "",
        "Owned": "FALSE",
        "Last Scrape": "2025-03-20 18:12"
    },
    {
        "Release Date": "2025-06",
        "Set": "Final Fantasy (Play)",
        "Link": "https://www.tcgplayer.com/product/618889/magic-universes-beyond-final-fantasy-universes-beyond-final-fantasy-play-booster-pack?Language=English&page=1",
        "Current Price": "$18.54",
        "Bought At": "",
        "Owned": "FALSE",
        "Last Scrape": "2025-03-20 18:12"
    },
    {
        "Release Date": "2025-06",
        "Set": "Final Fantasy (Collectors)",
        "Link": "https://www.tcgplayer.com/product/618892/magic-universes-beyond-final-fantasy-universes-beyond-final-fantasy-collector-booster-pack?Language=English&page=1",
        "Current Price": "$58.69",
        "Bought At": "",
        "Owned": "FALSE",
        "Last Scrape": "2025-03-20 18:12"
    },
    {
        "Release Date": "2025-08",
        "Set": "Edge of Eternities (Play)",
        "Link": "https://www.tcgplayer.com/product/619697/magic-edge-of-eternities-edge-of-eternities-play-booster?Language=English&page=1",
        "Current Price": "$9.75",
        "Bought At": "",
        "Owned": "FALSE",
        "Last Scrape": "2025-03-20 18:12"
    },
    {
        "Release Date": "2025-08",
        "Set": "Edge of Eternities (Collectors)",
        "Link": "https://www.tcgplayer.com/product/619696/magic-edge-of-eternities-edge-of-eternities-collector-booster?Language=English&page=1",
        "Current Price": "$29.96",
        "Bought At": "",
        "Owned": "FALSE",
        "Last Scrape": "2025-03-20 18:12"
    }
]